setup.py
gpg/__init__.py
gpg/callbacks.py
gpg/core.py
gpg/errors.py
gpg/results.py
gpg/util.py
gpg/../gpgme.i
gpg/../helpers.c
gpg/../helpers.h
gpg/../private.h
gpg/../version.py
gpg/constants/__init__.py
gpg/constants/create.py
gpg/constants/event.py
gpg/constants/import_type.py
gpg/constants/keysign.py
gpg/constants/md.py
gpg/constants/pk.py
gpg/constants/protocol.py
gpg/constants/sigsum.py
gpg/constants/status.py
gpg/constants/validity.py
gpg/constants/data/__init__.py
gpg/constants/data/encoding.py
gpg/constants/keylist/__init__.py
gpg/constants/keylist/mode.py
gpg/constants/sig/__init__.py
gpg/constants/sig/mode.py
gpg/constants/sig/notation.py
gpg/constants/tofu/__init__.py
gpg/constants/tofu/policy.py
gpgme.egg-info/PKG-INFO
gpgme.egg-info/SOURCES.txt
gpgme.egg-info/dependency_links.txt
gpgme.egg-info/top_level.txt