Metadata-Version: 2.2
Name: gpgme
Version: 2.0.0b4
Summary: Python bindings to the GPGME API of the GnuPG cryptography library.
Home-page: https://www.gnupg.org
Author: The GnuPG hackers
Author-email: gnupg-devel@gnupg.org
License: LGPL2.1+ (the library), GPL2+ (tests and examples)
Classifier: Development Status :: 4 - Beta
Classifier: Intended Audience :: Developers
Classifier: License :: OSI Approved :: GNU Lesser General Public License v2 or later (LGPLv2+)
Classifier: Programming Language :: Python :: 2
Classifier: Programming Language :: Python :: 2.7
Classifier: Programming Language :: Python :: 3
Classifier: Programming Language :: Python :: 3.6
Classifier: Programming Language :: Python :: 3.9
Classifier: Programming Language :: Python :: 3.10
Classifier: Programming Language :: Python :: 3.11
Classifier: Programming Language :: Python :: 3.12
Classifier: Programming Language :: Python :: 3.13
Classifier: Operating System :: POSIX
Classifier: Operating System :: Microsoft :: Windows
Classifier: Topic :: Communications :: Email
Classifier: Topic :: Security :: Cryptography
Dynamic: author
Dynamic: author-email
Dynamic: classifier
Dynamic: description
Dynamic: home-page
Dynamic: license
Dynamic: summary
